{"subjects": ["programming", "history", "English literature"], 
"resources": {"programming": 
    [
    {"url": "https://www.youtube.com/watch?v=dwVAR6HClmI", 
    "computer_language": "BASIC", "medium": "video"}, 

    {"url": "https://www.amazon.com/dp/0513017178/ref=dp_bookdescription?_encoding=UTF8&n=283155", 
    "computer_language": "unspecified", "medium": "book", "free": "no"}, 

    {"url": "https://ocw.mit.edu/courses/electrical-engineering-and-computer-science/6-00sc-introduction-to-computer-science-and-programming-spring-2011/", 
    "computer_language": "Python", "medium": "course", "free": "yes"}, 

    {"url": "https://www.coursera.org/learn/intro-programming", 
    "computer_language": "Scratch", "medium": "course", 

    "free": "you can audit some videos and course content"}

    ], 
    "history": []},
    "languages": [{"english": "I speak English", "french": "Je parle français", "mandarin": "我会中文（简体字）"}]
}
